Workbook

Sheet DATOS GERERALES
B2: ADN ANALISIS DE NECESIDADES | K2: PARA SEGUNDA CITA
J4: RESUMEN COMPROMISO EDUCATIVO
B5: Fecha de Consultoría | C5: 45982
C7: Nombre | D7: Edad | E7: EP | G7: ACTIVIDAD ECONOMICA | J7: COLEGIO | K7: ='EDUCACION HIJOS'!D10+'EDUCACION HIJOS'!D15+'EDUCACION HIJOS'!D20+'EDUCACION HIJOS'!D25+'EDUCACION HIJOS'!D30 -> 408000000
B8: Nombre Cliente | C8: CARLOS CERVANTES | D8: 34 | E8: 62 | G8: MÉDICO GENERAL | J8: UNIVERSIDAD | K8: ='EDUCACION HIJOS'!G16 -> 242000000
B9: Fecha NacimieNto | C9: 21 DE ENERO DE 1992 | G9: Salario / Honorarios | J9: TOTAL | K9: =K7+K8 -> 650000000
B10: Cédula | G10: 4000000
B11: Celular | J11: DESCOBERTURAS | L11: CAPITAL NECESARIO PARA TU PROTECCION
B12: Mail | G12: Ahorro y o Seguros | J12: Fallecimiento | K12: ='PANORAMA LEY 100'!D24 -> 557120000
B13: Estado Civil | J13: Invalidez | K13: ='PANORAMA LEY 100'!D25 -> 567680000
B14: Nombre Cónyuge | E14: 57 | J14: Pesnsion Público | K14: ='PANORAMA LEY 100'!D26 -> 518400000
B15: Fecha Nacimiento | G15: Rentas- Inversiones | J15: Pension Privado
B16: Hijo (a) | J16: Pension Sistema Pilares | K16: ='PANORAMA LEY 100'!D27 -> 549464000
B17: Hijo (a)
B18: Hijo (a) | G18: Gasto Mensual
B19: Hijo (a) | G19: 3000000
B20: Hijo (a)

Sheet PANORAMA LEY 100
B2: ANALISIS DE NECESIDADES | E2: ='DATOS GERERALES'!C8 -> CARLOS CERVANTES | G2: 1423500 | L2: ANALISIS BRECHA PENSIONAL | N2: ='DATOS GERERALES'!C14 -> 0 | Q2: 1423500
G3: =G2-(G2*0.12) -> 1252680 | Q3: =Q2-(Q2*0.125) -> 1245562.5
A4: EDAD | B4: Adm Pensión | C4: COLPENSIONES | E4: CALCULO PENSION INVALIDEZ | L4: Adm Pensión | O4: CALCULO PENSION INVALIDEZ
A5: 34 | B5: Años cotizados | C5: 5 | E5: 0.66 | F5: =IF((C9*E5)>G3,(C9*E5)*0.88,G3) -> 1161600 | L5: Años cotizados | M5: 21 | O5: % | P5: =IF((M9*O5)>Q3,(M9*O5)*0.88,Q3) -> #VALUE!
A6: 3 | B6: Años por cotizar | C6: 28 | L6: Años por cotizar
M7: ='DATOS GERERALES'!E14-'DATOS GERERALES'!D14 -> 57
B8: Ingreso Mensual | C8: 4000000 | E8: CALCULO PENSION SOBREVIVENCIA | L8: Ingreso Mensual | M8: ='DATOS GERERALES'!Q10 -> 0 | O8: CALCULO PENSION SOBREVIVENCIA
B9: Base Cotización últimos 10 años | C9: 2000000 | E9: 0.69 | F9: =IF((C9*E9)>G3,(C9*E9)*0.88,G3) -> 1214400 | L9: Base Cotización últimos 10 años | M9: =T29 -> 4892666.7 | O9: % | P9: =IF((M9*O9)>Q3,(M9*O9)*0.88,Q3) -> #VALUE!
B10: Ingreso Base de Cotización Actual | C10: 2000000 | L10: Ingreso Base de Cotización Actual | M10: 32500000
B12: RPMPD
B13: RPMPD COLPENSIONES | E13: RAIS FONDOS DE PENSIONES AFPs | H13: EDAD | I13: =A5 -> 34 | J13: % | L13: RPMPD | O13: RAIS
B14: PENSION VEJEZ COLPENSIONES | E14: PENSION VEJEZ FONDO PRIVADO | H14: SEMANAS COTIZADAS | I14: =C5*G15 -> 260 | L14: PENSION VEJEZ COLPENSIONES | O14: PENSION VEJEZ FONDO PRIVADO | Q14: MIN | R14: 54
B15: Años totales | C15: =C5+C6 -> 33 | E15: Capital necesario Fedesarrollo | F15: =377*($G$2) -> 536659500 | G15: 52 | H15: AÑOS FALTANTES | I15: =C6 -> 28 | L15: Años totales | M15: =M5+M7 -> 78 | O15: Capital necesario Fedesarrollo | P15: =377*($G$2) -> 536659500
B16: Semanas a Acumular | C16: =C15*52 -> 1716 | E16: Acumulación proyectada | F16: =((C10*0.115)*12*(C5+C6)) -> 91080000 | H16: ALCANCE DE SEMANAS + | I16: =I15*G15 -> 1456 | L16: Semanas a Acumular | M16: =M15*50 -> 3900 | O16: Acumulación proyectada | P16: =((M10*0.115)*12*(M5+M7)) -> 3498300000
B17: Penalización Fórmula | C17: =(((C10/$G$2)*0.5)/100)-0.5% -> 0.0020249385 | E17: # Veces Capital Necesario | F17: =F16/F15 -> 0.16971655 | H17: TOTAL | I17: =I14+I16 -> 1716 | L17: Penaización Fórmula | M17: =(((M11/$G$2)*0.5)/100)-0.5% -> -0.005 | O17: # Veces Capital Necesario | P17: =P16/P15 -> 6.5186585
B18: Tasa de Reemplazo (%) | C18: 0.8 | F18: =((G2*F17*0.88)) -> 212600.53 | L18: Tasa de Reemplazo (%) | M18: 0.67 | P18: =((Q2*P17*0.88)) -> 8165793.1
B19: PENSION NETA | C19: =IF((C10*C18*0.875)>G3,C10*C18*0.88,G3) -> 1408000 | E19: PENSION NETA | F19: =IF(F18<G2,G3,F18) -> 1252680 | L19: PENSION NETA | M19: =IF((M10*M18*0.875)>Q3,M10*M18*0.88,Q3) -> 19162000 | O19: PENSION NETA | P19: =IF(P18<Q2,Q3,P18) -> 8165793.1 | R19: 70.5
I21: 1650 | J21: 0.755
B22: DESCOBERTURAS O BRECHAS PENSIONALES | C22: BRECHA O DEFICIT PENSIONAL | D22: CAPITAL NECESARIO | F22: LIBERTAD FINANCIERA POR RENTA MENSUAL | G22: LIBERTAD FINANCIERA POR RENTA MENSUAL | I22: 1700 | J22: 0.77 | L22: DESCOBERTURAS O BRECHAS PENSIONALES | M22: BRECHA O DEFICIT PENSIONAL | N22: CAPITAL NECESARIO | P22: LIBERTAD FINANCIERA POR RENTA MENSUAL | Q22: LIBERTAD FINANCIERA POR RENTA MENSUAL
I23: 1750 | J23: 0.785
B24: Fallecimiento | C24: =C8-F9 -> 2785600 | D24: =C24*200 -> 557120000 | F24: 0.005 | G24: =D24*F24 -> 2785600 | I24: 1800 | J24: 0.8 | L24: Fallecimiento | M24: =M8-P9 -> #VALUE! | N24: ='EDUCACION HIJOS'!Q13 -> 0 | P24: 0.005 | Q24: =N24*P24 -> 0
B25: Invalidez | C25: =C8-F5 -> 2838400 | D25: =C25*200 -> 567680000 | F25: 0.005 | G25: =D25*F25 -> 2838400 | L25: Invalidez | M25: =M8-P5 -> #VALUE! | N25: =M25*200 -> #VALUE! | P25: 0.005 | Q25: =N25*P25 -> #VALUE!
B26: Vejez Transición Colpension | C26: =C8-C19 -> 2592000 | D26: =(C26*200) -> 518400000 | F26: 0.005 | G26: =D26*F26 -> 2592000 | I26: 2014 | J26: 2163000 | L26: Vejez Transición Colpension | M26: =M8-M19 -> -19162000 | N26: =M26*200 -> -3832400000 | P26: 0.005 | Q26: =N26*P26 -> -19162000 | S26: 2014 | T26: 2163000
B27: Vejez ley 100 Fondo Privado | C27: =C8-F19 -> 2747320 | D27: =(C27*200) -> 549464000 | F27: 0.005 | G27: =D27*F27 -> 2747320 | I27: 2019 | J27: 8500000 | L27: Vejez ley 100 Fondo Privado | M27: =M8-P19 -> -8165793.1 | N27: =M27*200 -> -1.6331586e+09 | P27: 0.005 | Q27: =N27*P27 -> -8165793.1 | S27: 2019 | T27: 8500000
B28: Universidad | C28: ='EDUCACION HIJOS'!G16 -> 242000000 | D28: ='EDUCACION HIJOS'!G16 -> 242000000 | I28: 2024 | J28: 4015000 | L28: Universidad | M28: ='EDUCACION HIJOS'!Q16 -> 0 | N28: ='EDUCACION HIJOS'!Q16 -> 0 | P28: 0.005 | Q28: =N28*P28 -> 0 | S28: 2024 | T28: 4015000
J29: =AVERAGE(J26:J28) -> 4892666.7 | T29: =AVERAGE(T26:T28) -> 4892666.7

Sheet PANORAMA REFORMA
B2: ANALISIS BRECHA PENSIONAL | D2: ='DATOS GERERALES'!C8 -> CARLOS CERVANTES | G2: 1423500 | L2: ANALISIS BRECHA PENSIONAL | N2: ='DATOS GERERALES'!C14 -> 0 | Q2: 1423500
G3: =G2-(G2*0.125) -> 1245562.5 | Q3: =Q2-(Q2*0.125) -> 1245562.5
A4: EDAD | B4: Adm Pensión | E4: CALCULO PENSION INVALIDEZ | L4: Adm Pensión | O4: CALCULO PENSION INVALIDEZ
A5: ='PANORAMA LEY 100'!A5 -> 34 | B5: Años cotizados | D5: 52 | F5: =IF((C9*E5)>G3,(C9*E5)*0.88,G3) -> 1245562.5 | L5: Años cotizados | O5: % | P5: =IF((M9*O5)>Q3,M9*O5,Q3) -> #VALUE!
A6: 62 | B6: Años por cotizar | C6: 28 | L6: Años por cotizar | M6: ='DATOS GERERALES'!E14-'DATOS GERERALES'!D14 -> 57
B8: Ingreso Mensual | E8: CALCULO PENSION SOBREVIVENCIA | L8: Ingreso Mensual | M8: ='DATOS GERERALES'!Q10 -> 0 | O8: CALCULO PENSION SOBREVIVENCIA
B9: Base Cotización últimos 10 años | F9: =IF((C9*E9)>G3,(C9*E9)*0.88,G3) -> 1245562.5 | L9: Base Cotización últimos 10 años | O9: % | P9: =IF((M9*O9)>Q3,M9*O9,Q3) -> #VALUE!
B10: Ingreso Base de Cotización Actual | L10: Ingreso Base de Cotización Actual
B11: IBC Colpensiones | C11: =1423500*2.3 -> 3274050 | L11: IBC Colpensiones | M11: =IF(M10>(2.3*Q2),2.3*Q2,M10) -> 0
B12: IBC Fondo Privado | C12: =C10-C11 -> -3274050 | I12: EDAD | J12: =A5 -> 34 | L12: IBC Fondo Privado | M12: =M10-M11 -> 0
B14: COLPENSIONES RPMPD | E14: ACCAI | I14: SEMANAS COTIZADAS | J14: 260 | L14: RPMPD | O14: RAIS
B15: PENSION VEJEZ COLPENSIONES | E15: PENSION VEJEZ FONDO PRIVADO | H15: 54 | I15: AÑOS FALTANTES | J15: =C6 -> 28 | L15: PENSION VEJEZ COLPENSIONES | O15: PENSION VEJEZ FONDO PRIVADO | Q15: MIN | R15: 54
B16: Años totales | C16: =C5+C6 -> 28 | E16: Capital necesario Fedesarrollo | F16: =377*($G$2) -> 536659500 | I16: ALCANCE DE SEMANAS + | J16: =C6*D5 -> 1456 | L16: Años totales | M16: =M5+M6 -> 57 | O16: Capital necesario Fedesarrollo | P16: =377*($G$2) -> 536659500
B17: Semanas a Acumular | C17: =C16*52 -> 1456 | E17: Acumulación proyectada | F17: =((C10*0.115)*12*(C5+C6)) -> 0 | I17: TOTAL | J17: =J14+J16 -> 1716 | L17: Semanas a Acumular | M17: =M16*52 -> 2964 | O17: Acumulación proyectada | P17: =((M10*0.115)*12*(M5+M6)) -> 0
B18: Penaización Fórmula | C18: =(((C11/$G$2)*0.5)/100)-0.5% -> 0.0065 | E18: # Veces Capital Necesario | F18: =F17/F16 -> 0 | L18: Penaización Fórmula | M18: =(((M11/$G$2)*0.5)/100)-0.5% -> -0.005 | O18: # Veces Capital Necesario | P18: =P17/P16 -> 0
B19: Tasa de Reemplazo (%) | C19: 0.71 | F19: =((G2*F18*0.88)) -> 0 | L19: Tasa de Reemplazo (%) | M19: 0.68 | P19: =((Q2*P18*0.88)) -> 0
B20: PENSION NETA | C20: =IF((C11*C19*0.88)>G3,C11*C19*0.88,G3) -> 2045626.4 | E20: PENSION NETA | F20: =(1.1*G2*F17/F16)*0.88 -> 0 | I20: 1600 | J20: 0.74 | L20: PENSION NETA | M20: =IF((M11*M19*0.88)>Q3,M11*M19*0.88,Q3) -> 1245562.5 | O20: PENSION NETA | P20: =1.1*Q2*P17/P16 -> 0
I21: 1650 | J21: 0.755
B22: PENSION TOTAL DEL SISTEMA | E22: =(C20+F20) -> 2045626.4 | H22: 70.5 | I22: 1700 | J22: 0.77 | L22: PENSION TOTAL DEL SISTEMA | O22: =(M20+P20)*0.875 -> 1089867.2 | R22: 70.5
I23: 1750 | J23: 0.785
I24: 1800 | J24: 0.8
B25: DESCOBERTURAS O BRECHAS PENSIONALES | C25: BRECHA O DEFICIT PENSIONAL | D25: CAPITAL NECESARIO | F25: LIBERTAD FINANCIERA POR RENTA MENSUAL | G25: LIBERTAD FINANCIERA POR RENTA MENSUAL | L25: DESCOBERTURAS O BRECHAS PENSIONALES | M25: BRECHA O DEFICIT PENSIONAL | N25: CAPITAL NECESARIO | P25: LIBERTAD FINANCIERA POR RENTA MENSUAL | Q25: LIBERTAD FINANCIERA POR RENTA MENSUAL
B27: Fallecimiento | C27: =C8-F9 -> -1245562.5 | D27: =C27*200 -> -249112500 | F27: 0.005 | G27: =D27*F27 -> -1245562.5 | L27: Fallecimiento | M27: =M10-P9 -> #VALUE! | N27: ='EDUCACION HIJOS'!Q13 -> 0 | P27: 0.005 | Q27: =N27*P27 -> 0
B28: Invalidez | C28: =C8-F5 -> -1245562.5 | D28: =C28*200 -> -249112500 | F28: 0.005 | G28: =D28*F28 -> -1245562.5 | L28: Invalidez | M28: =M10-P5 -> #VALUE! | N28: =M28*200 -> #VALUE! | P28: 0.005 | Q28: =N28*P28 -> #VALUE!
B29: Vejez | C29: =C8-E22 -> -2045626.4 | D29: =D28/2.5 -> -99645000 | F29: 0.005 | G29: =D29*F29 -> -498225 | L29: Vejez | M29: =M10-O22 -> -1089867.2 | N29: =M29*200 -> -2.1797344e+08 | P29: 0.005 | Q29: =N29*P29 -> -1089867.2
B31: Universidad | D31: ='EDUCACION HIJOS'!G16 -> 242000000
B41: IBC ACTUAL | C41: COTIZACION OBLIGATORIA | L41: IBC ACTUAL | M41: COTIZACION OBLIGATORIA
B42: 1423500 | C42: SALUD | D42: 0.125 | E42: =D42*B42 -> 177937.5 | M42: SALUD | N42: 0.125 | O42: =L42*N42 -> 0
C43: PENSION | D43: 0.16 | E43: =D43*B42 -> 227760 | M43: PENSION | N43: 0.16 | O43: =L43*N43 -> 0
C44: FONDO SOLIDARIDAD | D44: 0 | E44: =D44*B42 -> 0 | M44: FONDO SOLIDARIDAD | N44: 0.015 | O44: =L42*N44 -> 0
B45: PAGO MENSUAL PROYECTADO | E45: =SUM(E42:E44) -> 405697.5 | L45: PAGO MENSUAL PROYECTADO | O45: =SUM(O42:O44) -> 0
B48: IBC ACTUAL | C48: COTIZACION OBLIGATORIA | L48: IBC ACTUAL | M48: COTIZACION OBLIGATORIA
C49: SALUD | D49: 0.125 | E49: =D49*B49 -> 0 | M49: SALUD | N49: 0.125 | O49: =L49*N49 -> 0
C50: PENSION | D50: 0.16 | E50: =D50*B49 -> 0 | M50: PENSION | N50: 0.16 | O50: =L49*N50 -> 0
C51: FONDO SOLIDARIDAD | D51: 0.01 | E51: =D51*B49 -> 0 | M51: FONDO SOLIDARIDAD | N51: 0.015 | O51: =L49*N51 -> 0
B52: PAGO MENSUAL PROYECTADO | E52: =SUM(E49:E51) -> 0 | L52: PAGO MENSUAL PROYECTADO | O52: =SUM(O49:O51) -> 0
B55: INCREMENTO COTIZACION | E55: =E52-E45 -> -405697.5 | L55: INCREMENTO COTIZACION | O55: =O52-O45 -> 0
B56: AÑOS FALTANTES | D56: 5 | L56: AÑOS FALTANTES
B57: TOTAL PAGO PROYECTADO | E57: =(E55*D56)*12 -> -24341850 | L57: TOTAL PAGO PROYECTADO | O57: =(O55*N56)*12 -> 0
B58: MEJORAMIENTO PENSION VEJEZ | L58: MEJORAMIENTO PENSION VEJEZ

Sheet EDUCACION HIJOS
B2: Nombre Hijos | C2: Edad | D2: Años Faltantes
B3: ='DATOS GERERALES'!C16 -> 0 | C3: ='DATOS GERERALES'!D16 -> 0 | D3: =17-C3 -> 17
B4: ='DATOS GERERALES'!C17 -> 0 | C4: ='DATOS GERERALES'!D17 -> 0 | D4: =17-C4 -> 17
B5: ='DATOS GERERALES'!C18 -> 0 | C5: ='DATOS GERERALES'!D18 -> 0 | D5: =17-C5 -> 17
B6: ='DATOS GERERALES'!C19 -> 0 | C6: ='DATOS GERERALES'!D19 -> 0 | D6: =17-C6 -> 17
B7: ='DATOS GERERALES'!C20 -> 0 | C7: ='DATOS GERERALES'!D20 -> 0 | D7: =17-C7 -> 17
B9: =B3 -> 0
B10: Colegio Pensión | C10: 800000 | D10: =+C10*12*D3 -> 163200000 | F10: DESCOBERTURA EDUCATIVA | G10: =+D12+D17+D22+D27+D32 -> 650000000
B11: Universidad Semestre | C11: 11000000 | D11: =+C11*10 -> 110000000 | F11: Seguro eductiva o inversión | G11: 0
B12: TOTAL | D12: =+D10+D11 -> 273200000 | F12: Deuda Educativa Descubierta | G12: =+G10-G11 -> 650000000
F13: VALOR DE SEGURO DE VIDA SUGERIDO | G13: =G12 -> 650000000 | H13: 0.4
B14: =B4 -> 0
B15: Colegio Pensión | C15: 1200000 | D15: =+C15*12*D4 -> 244800000
B16: Universidad Semestre | C16: 11000000 | D16: =+C16*12 -> 132000000 | F16: ACUMULACION NECESARIA UNIVERSIDAD | G16: =+D11+D16+D21+D26+D31 -> 242000000
B17: TOTAL | D17: =+D15+D16 -> 376800000
B19: =B5 -> 0
B20: Colegio Pensión | D20: =+C20*12*D5 -> 0
B21: Universidad Semestre | D21: =+C21*10 -> 0
B22: TOTAL | D22: =+D20+D21 -> 0
B24: =B6 -> 0
B25: Colegio Pensión | D25: =+C25*12*D6 -> 0
B26: Universidad Semestre | D26: =+C26*10 -> 0
B27: TOTAL | D27: =+D25+D26 -> 0
B29: =B7 -> 0
B30: Colegio Pensión | D30: =+C30*12*D7 -> 0
B31: Universidad Semestre | D31: =+C31*10 -> 0
B32: TOTAL | D32: =+D30+D31 -> 0
